azure_updates_mcp/__init__.py
azure_updates_mcp/server.py
azure_updates_mcp/feeds/__init__.py
azure_updates_mcp/feeds/azure_api.py
azure_updates_mcp/models/__init__.py
azure_updates_mcp/models/update.py
azure_updates_mcp/tools/__init__.py
azure_updates_mcp/tools/search.py
azure_updates_mcp-0.3.0.dist-info/METADATA
azure_updates_mcp-0.3.0.dist-info/WHEEL
azure_updates_mcp-0.3.0.dist-info/entry_points.txt
azure_updates_mcp-0.3.0.dist-info/licenses/LICENSE
azure_updates_mcp-0.3.0.dist-info/RECORD
