Metadata-Version: 2.4
Name: azure-updates-mcp
Version: 0.3.0
Summary: MCP server for Azure Updates JSON API
Project-URL: Homepage, https://github.com/jonnybottles/azure-updates-mcp
Project-URL: Repository, https://github.com/jonnybottles/azure-updates-mcp
Project-URL: Issues, https://github.com/jonnybottles/azure-updates-mcp/issues
Author: azure-updates-mcp contributors
License: MIT
License-File: LICENSE
Keywords: api,azure,mcp,model-context-protocol,updates
Classifier: Development Status :: 3 - Alpha
Classifier: Intended Audience :: Developers
Classifier: License :: OSI Approved :: MIT License
Classifier: Programming Language :: Python :: 3
Classifier: Programming Language :: Python :: 3.11
Classifier: Programming Language :: Python :: 3.12
Classifier: Topic :: Software Development :: Libraries :: Python Modules
Requires-Python: >=3.11
Requires-Dist: fastmcp<3,>=2.14
Requires-Dist: httpx>=0.28
Requires-Dist: pydantic>=2.0
Provides-Extra: dev
Requires-Dist: pytest-asyncio>=0.24; extra == 'dev'
Requires-Dist: pytest>=8.0; extra == 'dev'
Requires-Dist: ruff>=0.8; extra == 'dev'
